configue_cli/__init__.py
configue_cli/click.py
configue_cli/py.typed
configue_cli/core/__init__.py
configue_cli/core/configue_cli.py
configue_cli/core/dict_config.py
configue_cli/core/dumper.py
configue_cli/core/exceptions.py
configue_cli/core/loader.py
configue_cli/core/missing.py
configue_cli/core/render.py
configue_cli/core/traversers.py
configue_cli-0.2.0.dist-info/LICENSE
configue_cli-0.2.0.dist-info/METADATA
configue_cli-0.2.0.dist-info/WHEEL
configue_cli-0.2.0.dist-info/top_level.txt
configue_cli-0.2.0.dist-info/RECORD
