Metadata-Version: 2.1
Name: configue-cli
Version: 0.2.0
Summary: A configue extension that adds the ability to dynamically configure your application via the command line.
Author-email: Illuin Technology <contact@illuin.tech>
Maintainer-email: Illuin Technology <contact@illuin.tech>
Project-URL: homepage, https://github.com/illuin-tech/configue-cli
Project-URL: repository, https://github.com/illuin-tech/configue-cli
Platform: any
Classifier: Development Status :: 4 - Beta
Classifier: Intended Audience :: Science/Research
Classifier: Intended Audience :: Developers
Classifier: License :: OSI Approved :: MIT License
Classifier: Operating System :: OS Independent
Classifier: Programming Language :: Python :: 3
Classifier: Programming Language :: Python :: 3.7
Classifier: Programming Language :: Python :: 3.8
Classifier: Programming Language :: Python :: 3.9
Classifier: Programming Language :: Python :: 3.10
Classifier: Programming Language :: Python :: 3.11
Classifier: Topic :: Scientific/Engineering :: Artificial Intelligence
Classifier: Typing :: Typed
Requires-Python: >=3.7
License-File: LICENSE
Requires-Dist: attrs (>=22.0.0)
Requires-Dist: click (>=8.0.0)
Requires-Dist: configue (>=4.0.0)
Requires-Dist: pyyaml (>=5.1.0)
Requires-Dist: rich (>=13.0.0)
Provides-Extra: skypilot
Requires-Dist: skypilot (==0.2.5) ; (python_version < "3.11") and extra == 'skypilot'
